matrx_utils/__init__.py
matrx_utils/conf.py
matrx_utils/data_handling/__init__.py
matrx_utils/data_handling/data_transformer.py
matrx_utils/data_handling/utils.py
matrx_utils/data_handling/validation/__init__.py
matrx_utils/data_handling/validation/errors.py
matrx_utils/data_handling/validation/validators.py
matrx_utils/fancy_prints/__init__.py
matrx_utils/fancy_prints/colors.py
matrx_utils/fancy_prints/fancy_prints.py
matrx_utils/fancy_prints/matrx_print_logger.py
matrx_utils/fancy_prints/redaction.py
matrx_utils/fancy_prints/utils/__init__.py
matrx_utils/fancy_prints/utils/matrx_json_converter.py
matrx_utils/field_processing/__init__.py
matrx_utils/field_processing/dataclass_generator.py
matrx_utils/field_processing/field_handler.py
matrx_utils/file_handling/__init__.py
matrx_utils/file_handling/base_handler.py
matrx_utils/file_handling/batch_handler.py
matrx_utils/file_handling/file_handler.py
matrx_utils/file_handling/file_manager.py
matrx_utils/file_handling/local_files.py
matrx_utils/file_handling/specific_handlers/__init__.py
matrx_utils/file_handling/specific_handlers/code_handler.py
matrx_utils/file_handling/specific_handlers/html_handler.py
matrx_utils/file_handling/specific_handlers/image_handler.py
matrx_utils/file_handling/specific_handlers/json_handler.py
matrx_utils/file_handling/specific_handlers/markdown_handler.py
matrx_utils/file_handling/specific_handlers/text_handler.py
matrx_utils/utils/__init__.py
matrx_utils/utils/clear_terminal.py
matrx_utils/utils/get_dir_structure.py
matrx_utils/utils/testing.py
matrx_utils-1.0.3.dist-info/METADATA
matrx_utils-1.0.3.dist-info/WHEEL
matrx_utils-1.0.3.dist-info/entry_points.txt
matrx_utils-1.0.3.dist-info/RECORD
