Metadata-Version: 2.4
Name: matrx-utils
Version: 1.0.3
Summary: Basic utilities for matrx
Author-email: jatin.b.rx3@gmail.com
Requires-Python: >=3.10
Requires-Dist: dotenv>=0.9.9
Requires-Dist: inflect>=7.5.0
Requires-Dist: pillow>=11.2.1
Requires-Dist: requests>=2.32.5
